odoo8_addon_medical_disease-8.0.1.1.0.99.dev5-py2.7-nspkg.pth
odoo8_addon_medical_disease-8.0.1.1.0.99.dev5.dist-info/DESCRIPTION.rst
odoo8_addon_medical_disease-8.0.1.1.0.99.dev5.dist-info/METADATA
odoo8_addon_medical_disease-8.0.1.1.0.99.dev5.dist-info/RECORD
odoo8_addon_medical_disease-8.0.1.1.0.99.dev5.dist-info/WHEEL
odoo8_addon_medical_disease-8.0.1.1.0.99.dev5.dist-info/metadata.json
odoo8_addon_medical_disease-8.0.1.1.0.99.dev5.dist-info/namespace_packages.txt
odoo8_addon_medical_disease-8.0.1.1.0.99.dev5.dist-info/top_level.txt
odoo_addons/medical_disease/README.rst
odoo_addons/medical_disease/__init__.py
odoo_addons/medical_disease/__openerp__.py
odoo_addons/medical_disease/i18n/pt_BR.po
odoo_addons/medical_disease/i18n/sl.po
odoo_addons/medical_disease/models/__init__.py
odoo_addons/medical_disease/models/medical_pathology.py
odoo_addons/medical_disease/models/medical_pathology_category.py
odoo_addons/medical_disease/models/medical_pathology_group.py
odoo_addons/medical_disease/models/medical_patient.py
odoo_addons/medical_disease/models/medical_patient_disease.py
odoo_addons/medical_disease/security/ir.model.access.csv
odoo_addons/medical_disease/tests/__init__.py
odoo_addons/medical_disease/tests/test_medical_disease.py
odoo_addons/medical_disease/views/medical_disease_view.xml
odoo_addons/medical_disease/views/medical_pathology_category_view.xml
odoo_addons/medical_disease/views/medical_pathology_group_view.xml
odoo_addons/medical_disease/views/medical_pathology_view.xml
odoo_addons/medical_disease/views/medical_patient_disease_view.xml
odoo_addons/medical_disease/views/medical_patient_view.xml
